MANIFEST.in
README.txt
setup.py
wofrywise2/__init__.py
wofrywise2/version.py
wofrywise2.egg-info/PKG-INFO
wofrywise2.egg-info/SOURCES.txt
wofrywise2.egg-info/dependency_links.txt
wofrywise2.egg-info/not-zip-safe
wofrywise2.egg-info/requires.txt
wofrywise2.egg-info/top_level.txt
wofrywise2/_test/__init__.py
wofrywise2/_test/simulazione_dpi_per_rebuffi.py
wofrywise2/_test/simulazione_dpi_per_rebuffi_2.py
wofrywise2/_test/test_manfredda_to_wofry.py
wofrywise2/_test/test_manfredda_to_wofry_2.py
wofrywise2/beamline/__init__.py
wofrywise2/beamline/wise_beamline_element.py
wofrywise2/beamline/wise_optical_element.py
wofrywise2/beamline/light_sources/__init__.py
wofrywise2/beamline/light_sources/wise_gaussian_source.py
wofrywise2/beamline/light_sources/wise_point_source.py
wofrywise2/beamline/optical_elements/__init__.py
wofrywise2/beamline/optical_elements/wise_detector.py
wofrywise2/beamline/optical_elements/wise_elliptic_mirror.py
wofrywise2/beamline/optical_elements/wise_plane_mirror.py
wofrywise2/beamline/optical_elements/wise_spheric_mirror.py
wofrywise2/propagator/__init__.py
wofrywise2/propagator/propagator1D/__init__.py
wofrywise2/propagator/propagator1D/wise_propagator.py
wofrywise2/propagator/wavefront1D/__init__.py
wofrywise2/propagator/wavefront1D/wise_wavefront.py