Metadata-Version: 1.2
Name: wofrywise2
Version: 1.0.1
Summary: WOFRY (Wave Optics FRamework in pYthon) for WISE 2 library
Home-page: https://github.com/oasys-elettra-kit/wofrywise2
Author: Luca Rebuffi
Author-email: luca.rebuffi@elettra.eu
Maintainer: Luca Rebuffi
Maintainer-email: luca.rebuffi@elettra.eu
License: GPLv3
Download-URL: https://github.com/oasys-elettra-kit/wofrywise2
Keywords: dictionary,glossary,synchrotronsimulation
Platform: UNKNOWN
Classifier: Development Status :: 1 - Planning
Classifier: Environment :: Console
Classifier: Environment :: Plugins
Classifier: Programming Language :: Python :: 3
Classifier: License :: OSI Approved :: GNU General Public License v3 or later (GPLv3+)
Classifier: Operating System :: POSIX
Classifier: Operating System :: Microsoft :: Windows
Classifier: Topic :: Scientific/Engineering :: Visualization
Classifier: Topic :: Software Development :: Libraries :: Python Modules
Classifier: Intended Audience :: Education
Classifier: Intended Audience :: Science/Research
Classifier: Intended Audience :: Developers
